<repast.simphony.data2.engine.FileSinkDescriptor simphonyVersion="2.6.0">
  <name>BatchRunOutput</name>
  <dataSet>BatchRunOutput</dataSet>
  <delimiter>,</delimiter>
  <format>TABULAR</format>
  <sourceIds class="linked-hash-set">
    <string>run</string>
    <string>tick</string>
    <string>random_seed</string>
    <string>Produced</string>
    <string>Deleted</string>
    <string>Consumed</string>
    <string>Cut Source</string>
    <string>Cut Produced</string>
    <string>Consumed Low</string>
    <string>Consumed High</string>
    <string>Quality ES High</string>
    <string>Quality ES Low</string>
    <string>Quality NL High</string>
    <string>Quality NL Low</string>
  </sourceIds>
  <fileName>output\BatchOutput\BatchRunOutput.txt</fileName>
  <addTimeStamp>true</addTimeStamp>
</repast.simphony.data2.engine.FileSinkDescriptor>