<repast.simphony.visualization.engine.CartesianDisplayDescriptor simphonyVersion="2.6.0">
  <name>Display 4 - Only Show Active Agents</name>
  <type>2D</type>
  <styles>
    <entry>
      <string>supplyChainModel.styles.VisualSCType</string>
      <string>supplyChainModel.styles.SCTypeStyle2D</string>
    </entry>
    <entry>
      <string>supplyChainModel.DataCollector</string>
      <string>supplyChainModel.styles.DataCollector2D</string>
    </entry>
    <entry>
      <string>supplyChainModel.support.Shipment</string>
      <string>supplyChainModel.styles.ShipmentStyle2D</string>
    </entry>
    <entry>
      <string>supplyChainModel.agents.BaseAgent</string>
      <string>supplyChainModel.styles.AgentStyle2D2_ACTIVE</string>
    </entry>
    <entry>
      <string>supplyChainModel.support.Order</string>
      <string>supplyChainModel.styles.OrderStyle2D</string>
    </entry>
    <entry>
      <string>supplyChainModel.agents.CountryAgent</string>
      <string>supplyChainModel.styles.CountryAgentStyle2D</string>
    </entry>
  </styles>
  <editedStyles>
    <entry>
      <string>supplyChainModel.styles.VisualSCType</string>
      <null/>
    </entry>
    <entry>
      <string>supplyChainModel.DataCollector</string>
      <null/>
    </entry>
    <entry>
      <string>supplyChainModel.support.Shipment</string>
      <null/>
    </entry>
    <entry>
      <string>supplyChainModel.agents.BaseAgent</string>
      <null/>
    </entry>
    <entry>
      <string>supplyChainModel.support.Order</string>
      <null/>
    </entry>
    <entry>
      <string>supplyChainModel.agents.CountryAgent</string>
      <null/>
    </entry>
  </editedStyles>
  <netStyles>
    <entry>
      <string>sc network reversed</string>
      <string>supplyChainModel.styles.SCReversedEdgeStyleOGL2D2_SHIPMENT</string>
    </entry>
    <entry>
      <string>sc network</string>
      <string>supplyChainModel.styles.SCEdgeStyleOGL2D_SHIPMENT</string>
    </entry>
  </netStyles>
  <editedNetStyles>
    <entry>
      <string>sc network reversed</string>
      <null/>
    </entry>
    <entry>
      <string>sc network</string>
      <null/>
    </entry>
  </editedNetStyles>
  <frequency>ON_MOVE</frequency>
  <schedParams>
    <start>1.0</start>
    <interval>1.0</interval>
    <priority>-Infinity</priority>
    <pType>LAST</pType>
    <duration>-1.0</duration>
    <frequency>REPEAT</frequency>
    <hashCode>-1650634587</hashCode>
  </schedParams>
  <layoutClassName>foo.bar.baz</layoutClassName>
  <layoutProjection>continuous space</layoutProjection>
  <layoutInterval>0</layoutInterval>
  <layerOrder>
    <entry>
      <string>supplyChainModel.styles.VisualSCType</string>
      <int>1</int>
    </entry>
    <entry>
      <string>supplyChainModel.DataCollector</string>
      <int>0</int>
    </entry>
    <entry>
      <string>supplyChainModel.support.Shipment</string>
      <int>4</int>
    </entry>
    <entry>
      <string>supplyChainModel.agents.BaseAgent</string>
      <int>5</int>
    </entry>
    <entry>
      <string>supplyChainModel.support.Order</string>
      <int>3</int>
    </entry>
    <entry>
      <string>supplyChainModel.agents.CountryAgent</string>
      <int>2</int>
    </entry>
  </layerOrder>
  <projections>
    <repast.simphony.scenario.data.ProjectionData>
      <id>continuous space</id>
      <attributes/>
      <type>continuous space</type>
    </repast.simphony.scenario.data.ProjectionData>
    <repast.simphony.scenario.data.ProjectionData>
      <id>grid</id>
      <attributes/>
      <type>grid</type>
    </repast.simphony.scenario.data.ProjectionData>
    <repast.simphony.scenario.data.ProjectionData>
      <id>sc network</id>
      <attributes/>
      <type>network</type>
    </repast.simphony.scenario.data.ProjectionData>
    <repast.simphony.scenario.data.ProjectionData>
      <id>sc network reversed</id>
      <attributes/>
      <type>network</type>
    </repast.simphony.scenario.data.ProjectionData>
  </projections>
  <visualizationProperties class="repast.simphony.visualization.UnitSizeLayoutProperties">
    <unitSize>25.0</unitSize>
  </visualizationProperties>
  <projectionDescriptors>
    <entry>
      <string>sc network reversed</string>
      <repast.simphony.visualization.engine.DefaultProjectionDescriptor>
        <proj reference="../../../../projections/repast.simphony.scenario.data.ProjectionData[4]"/>
        <props/>
      </repast.simphony.visualization.engine.DefaultProjectionDescriptor>
    </entry>
    <entry>
      <string>continuous space</string>
      <repast.simphony.visualization.continuous.ContinuousProjectionDescriptor>
        <proj reference="../../../../projections/repast.simphony.scenario.data.ProjectionData"/>
        <props>
          <entry>
            <string>repast.simphony.visualization.continuous.ContinuousDecorator</string>
            <map>
              <entry>
                <string>COLOR</string>
                <int>-6697729</int>
              </entry>
              <entry>
                <string>UNIT_SIZE</string>
                <float>25.0</float>
              </entry>
              <entry>
                <string>SHOW</string>
                <boolean>true</boolean>
              </entry>
            </map>
          </entry>
        </props>
      </repast.simphony.visualization.continuous.ContinuousProjectionDescriptor>
    </entry>
    <entry>
      <string>sc network</string>
      <repast.simphony.visualization.engine.DefaultProjectionDescriptor>
        <proj reference="../../../../projections/repast.simphony.scenario.data.ProjectionData[3]"/>
        <props/>
      </repast.simphony.visualization.engine.DefaultProjectionDescriptor>
    </entry>
    <entry>
      <string>grid</string>
      <repast.simphony.visualization.grid.GridProjectionDescriptor>
        <proj reference="../../../../projections/repast.simphony.scenario.data.ProjectionData[2]"/>
        <props>
          <entry>
            <string>repast.simphony.visualization.grid.GridDecorator</string>
            <map>
              <entry>
                <string>COLOR</string>
                <int>-986896</int>
              </entry>
              <entry>
                <string>UNIT_SIZE</string>
                <float>25.0</float>
              </entry>
              <entry>
                <string>SHOW</string>
                <boolean>true</boolean>
              </entry>
            </map>
          </entry>
        </props>
      </repast.simphony.visualization.grid.GridProjectionDescriptor>
    </entry>
  </projectionDescriptors>
  <props/>
  <backgroundColor>
    <red>255</red>
    <green>255</green>
    <blue>255</blue>
    <alpha>255</alpha>
  </backgroundColor>
  <valueLayers/>
</repast.simphony.visualization.engine.CartesianDisplayDescriptor>